qiskit/providers/qrack/__init__.py
qiskit/providers/qrack/qrackerror.py
qiskit/providers/qrack/qrackjob.py
qiskit/providers/qrack/qrackprovider.py
qiskit/providers/qrack/sampler.py
qiskit/providers/qrack/version.py
qiskit/providers/qrack/backends/__init__.py
qiskit/providers/qrack/backends/ace_qasm_simulator.py
qiskit/providers/qrack/backends/qasm_simulator.py
qiskit_qrack_provider-0.17.1.dist-info/licenses/LICENSE
qiskit_qrack_provider-0.17.1.dist-info/METADATA
qiskit_qrack_provider-0.17.1.dist-info/WHEEL
qiskit_qrack_provider-0.17.1.dist-info/top_level.txt
qiskit_qrack_provider-0.17.1.dist-info/RECORD
