Metadata-Version: 2.4
Name: qiskit-qrack-provider
Version: 0.17.1
Summary: Qiskit Qrack Provider - Qrack High-Performance GPU simulation for Qiskit
Home-page: https://github.com/vm6502q/qiskit-qrack-provider
Author: Daniel Strano
Author-email: dan@unitary.fund
License: Apache 2.0
Keywords: qiskit qrack pyqrack simulator quantum addon backend
Classifier: Environment :: Console
Classifier: Intended Audience :: Developers
Classifier: Intended Audience :: Science/Research
Classifier: Operating System :: Microsoft :: Windows
Classifier: Operating System :: MacOS
Classifier: Operating System :: POSIX :: Linux
Classifier: Programming Language :: C++
Classifier: Programming Language :: Python :: 3.5
Classifier: Programming Language :: Python :: 3.6
Classifier: Programming Language :: Python :: 3.7
Classifier: Programming Language :: Python :: 3.8
Classifier: Programming Language :: Python :: 3.9
Classifier: Programming Language :: Python :: 3.10
Classifier: Topic :: Scientific/Engineering
License-File: LICENSE
Requires-Dist: numpy>=1.16.3
Requires-Dist: pandas
Requires-Dist: pyqrack>=1.21.0
Requires-Dist: qiskit>=2.0.0
Dynamic: author
Dynamic: author-email
Dynamic: classifier
Dynamic: description
Dynamic: description-content-type
Dynamic: home-page
Dynamic: keywords
Dynamic: license
Dynamic: license-file
Dynamic: requires-dist
Dynamic: summary
